pyPenred/__init__.py
pyPenred/psf.cpython-312-x86_64-linux-gnu.so
pyPenred/simulation.cpython-312-x86_64-linux-gnu.so
pypenred-1.14.0.4.dist-info/METADATA
pypenred-1.14.0.4.dist-info/WHEEL
pypenred-1.14.0.4.dist-info/top_level.txt
pypenred-1.14.0.4.dist-info/RECORD
pypenred-1.14.0.4.dist-info/licenses/LICENSE
