Metadata-Version: 2.4
Name: pyPenred
Version: 1.14.0.4
Summary: Python interface for penRed framework
Home-page: https://github.com/penred/penred
Author: PenRed Contributors
Author-email: vicent.gimenez.alventosa@gmail.com
Platform: Linux :: x86_64
Platform: Windows :: x86_64
Platform: Mac OS-X
Classifier: Programming Language :: Python :: 3
Classifier: Programming Language :: C++
Classifier: Operating System :: POSIX :: Linux
Classifier: Operating System :: Microsoft :: Windows
Classifier: Operating System :: MacOS
Requires-Python: >=3.8
License-File: LICENSE
Requires-Dist: pyyaml
Requires-Dist: numpy
Dynamic: author
Dynamic: author-email
Dynamic: classifier
Dynamic: description
Dynamic: description-content-type
Dynamic: home-page
Dynamic: license-file
Dynamic: platform
Dynamic: requires-dist
Dynamic: requires-python
Dynamic: summary
